kafka_log_handler/KafkaHandler.py
kafka_log_handler/__init__.py
kafka_log_handler-1.2.dist-info/DESCRIPTION.rst
kafka_log_handler-1.2.dist-info/METADATA
kafka_log_handler-1.2.dist-info/RECORD
kafka_log_handler-1.2.dist-info/WHEEL
kafka_log_handler-1.2.dist-info/metadata.json
kafka_log_handler-1.2.dist-info/top_level.txt
